moat/lib/ring/__init__.py
moat/lib/ring/_impl.py
moat/lib/ring/aio.py
moat_lib_ring-0.2.2.dist-info/licenses/LICENSE.txt
moat_lib_ring-0.2.2.dist-info/METADATA
moat_lib_ring-0.2.2.dist-info/WHEEL
moat_lib_ring-0.2.2.dist-info/top_level.txt
moat_lib_ring-0.2.2.dist-info/RECORD
